mom6/__init__.py
mom6/data_structure/__init__.py
mom6/data_structure/gen_cefi_data_structure.py
mom6/data_structure/gen_cefi_data_structure_derivative.py
mom6/data_structure/gen_cefi_data_structure_unverfied.py
mom6/data_structure/portal_data.py
mom6/data_structure/recreate_cefi_dir.py
mom6/mom6_module/__init__.py
mom6/mom6_module/mom6_bbv.py
mom6/mom6_module/mom6_density.py
mom6/mom6_module/mom6_detrend.py
mom6/mom6_module/mom6_export.py
mom6/mom6_module/mom6_forecast_tercile.py
mom6/mom6_module/mom6_ild.py
mom6/mom6_module/mom6_indexes.py
mom6/mom6_module/mom6_mhw.py
mom6/mom6_module/mom6_read.py
mom6/mom6_module/mom6_regrid.py
mom6/mom6_module/mom6_statistics.py
mom6/mom6_module/mom6_types.py
mom6/mom6_module/mom6_vector_rotate.py
mom6/mom6_module/time_series_processes.py
mom6/mom6_module/util.py
rmom6_preprocessing-0.19.0.dist-info/licenses/LICENSE.md
tests/__init__.py
tests/conftest.py
tests/test_mom6_read.py
rmom6_preprocessing-0.19.0.dist-info/METADATA
rmom6_preprocessing-0.19.0.dist-info/WHEEL
rmom6_preprocessing-0.19.0.dist-info/top_level.txt
rmom6_preprocessing-0.19.0.dist-info/RECORD
