Metadata-Version: 2.4
Name: rmom6_preprocessing
Version: 0.19.0
Summary: Regional MOM6 CEFI preprocessing and data access
Home-page: https://github.com/NOAA-CEFI-Portal/regional_mom6
Author: Chia-Wei Hsu
Author-email: Chia-Wei Hsu <chia-wei.hsu@noaa.gov>
License: BSD 3-Clause
Project-URL: Homepage, https://github.com/NOAA-CEFI-Portal/regional_mom6
Requires-Python: >=3.11
License-File: LICENSE.md
Requires-Dist: xarray
Requires-Dist: netcdf4
Requires-Dist: dask
Requires-Dist: pydap
Requires-Dist: pytest
Requires-Dist: beautifulsoup4
Requires-Dist: matplotlib
Requires-Dist: zarr==2.18.3
Requires-Dist: fsspec
Requires-Dist: s3fs
Requires-Dist: gcsfs
Requires-Dist: gsw
Requires-Dist: kerchunk
Dynamic: author
Dynamic: home-page
Dynamic: license-file
Dynamic: requires-python
